qal/__init__.py
qal/__init__.pyi
qal/data/__init__.py
qal/data/__init__.pyi
qal/data/_fetchers.py
qal/data/_registry.py
qal/examples/create_lung_reference.py
qal/examples/depth_resolution_example.py
qal/examples/distortion_full_fov_example.py
qal/examples/distortion_sub_fov_example.py
qal/examples/lung_phantom_example.py
qal/examples/rrt_manual_example.py
qal/examples/rrt_semi-automatic_example.py
qal/examples/uniformity_good_system_example.py
qal/examples/uniformity_poor_system_example.py
qal/examples/well_analyzer_example.py
qal/rta/__init__.py
qal/rta/data_visualizer/__init__.py
qal/rta/data_visualizer/depth_resolution_plotter.py
qal/rta/data_visualizer/distortion_visualizer.py
qal/rta/data_visualizer/rrt_data_plotter.py
qal/rta/data_visualizer/uniformity_visualizer.py
qal/rta/data_visualizer/well_data_plotter.py
qal/rta/image_analyzer/__init__.py
qal/rta/image_analyzer/depth_resolution_analyzer.py
qal/rta/image_analyzer/distortion_analyzer.py
qal/rta/image_analyzer/rrt_analyzer.py
qal/rta/image_analyzer/uniformity_analyzer.py
qal/rta/image_analyzer/well_analyzer.py
qal/rta/roi_extraction/__init__.py
qal/rta/roi_extraction/crop_depth_phantom.py
qal/rta/roi_extraction/rrt_roi.py
qal/rta/roi_extraction/rud_detector.py
qal/rta/roi_extraction/well_detector.py
qal/vpa/__init__.py
qal/vpa/quel_lung_phantom.py
quel_qal-0.2.5.dist-info/licenses/LICENSE
quel_qal-0.2.5.dist-info/METADATA
quel_qal-0.2.5.dist-info/WHEEL
quel_qal-0.2.5.dist-info/top_level.txt
quel_qal-0.2.5.dist-info/RECORD
