Metadata-Version: 2.4
Name: quel-qal
Version: 0.2.5
Summary: A Python library for analyzing Quel Imaging fluorescent phantoms and imaging targets.
Author: Emmanuel Mannoh, Eammon Littler, Ethan LaRochelle
Maintainer-email: "QUEL Imaging, LLC" <devops@quelimaging.com>
License: AGPL-3.0
Project-URL: homepage, https://github.com/QUEL-Imaging/quel-qal/wiki
Project-URL: repository, https://github.com/QUEL-Imaging/quel-qal/tree/main
Project-URL: documentation, https://github.com/QUEL-Imaging/quel-qal/wiki
Keywords: image-processing,scientific-computing,data-analysis,research,academia,image-analysis,python,machine-learning
Classifier: Programming Language :: Python :: 3.12
Classifier: License :: OSI Approved :: GNU Affero General Public License v3
Classifier: Intended Audience :: Science/Research
Classifier: Intended Audience :: Education
Classifier: Topic :: Scientific/Engineering :: Image Recognition
Classifier: Topic :: Scientific/Engineering :: Image Processing
Classifier: Topic :: Software Development :: Libraries :: Python Modules
Classifier: Operating System :: OS Independent
Requires-Python: >=3.12
License-File: LICENSE
Requires-Dist: ipympl
Requires-Dist: matplotlib==3.9.2
Requires-Dist: numba
Requires-Dist: numpy
Requires-Dist: opencv-python
Requires-Dist: openpyxl
Requires-Dist: pandas
Requires-Dist: pooch
Requires-Dist: roipoly
Requires-Dist: scikit-image
Requires-Dist: scikit-learn
Requires-Dist: scipy
Requires-Dist: statsmodels
Requires-Dist: tqdm
Requires-Dist: lazy-loader
Dynamic: license-file
